openwakeword/__init__.py
openwakeword/model.py
openwakeword/utils.py
openwakeword/vad.py
openwakeword/resources/models/alexa_v0.1.onnx
openwakeword/resources/models/alexa_v0.1.tflite
openwakeword/resources/models/embedding_model.onnx
openwakeword/resources/models/embedding_model.tflite
openwakeword/resources/models/hey_jarvis_v0.1.onnx
openwakeword/resources/models/hey_jarvis_v0.1.tflite
openwakeword/resources/models/hey_mycroft_v0.1.onnx
openwakeword/resources/models/hey_mycroft_v0.1.tflite
openwakeword/resources/models/hey_rhasspy_v0.1.onnx
openwakeword/resources/models/hey_rhasspy_v0.1.tflite
openwakeword/resources/models/melspectrogram.onnx
openwakeword/resources/models/melspectrogram.tflite
openwakeword/resources/models/silero_vad.onnx
openwakeword/resources/models/timer_v0.1.onnx
openwakeword/resources/models/timer_v0.1.tflite
openwakeword/resources/models/weather_v0.1.onnx
openwakeword/resources/models/weather_v0.1.tflite
openwakeword_pruned-0.5.1.dist-info/LICENSE
openwakeword_pruned-0.5.1.dist-info/METADATA
openwakeword_pruned-0.5.1.dist-info/WHEEL
openwakeword_pruned-0.5.1.dist-info/top_level.txt
openwakeword_pruned-0.5.1.dist-info/RECORD
